README.md
setup.py
PyBark/__init__.py
PyBark.egg-info/PKG-INFO
PyBark.egg-info/SOURCES.txt
PyBark.egg-info/dependency_links.txt
PyBark.egg-info/top_level.txt