Metadata-Version: 1.0
Name: PyBark
Version: 0.2
Summary: A simple Bark application for notification
Home-page: https://github.com/MrReochen/PyBark
Author: Reo Chen
Author-email: reo@pku.edu.cn
License: MIT License
Keywords: pip,PyBark,Bark
Platform: any
